AUTHORS.rst
CONTRIBUTING.rst
HISTORY.rst
LICENSE
MANIFEST.in
README.md
setup.cfg
setup.py
docs/Makefile
docs/authors.rst
docs/conf.py
docs/contributing.rst
docs/history.rst
docs/index.rst
docs/installation.rst
docs/make.bat
docs/readme.rst
docs/usage.rst
pyosticket/__init__.py
pyosticket/pyosticket.py
pyosticket.egg-info/PKG-INFO
pyosticket.egg-info/SOURCES.txt
pyosticket.egg-info/dependency_links.txt
pyosticket.egg-info/not-zip-safe
pyosticket.egg-info/requires.txt
pyosticket.egg-info/top_level.txt
tests/test_pyosticket.py
tests/fixtures/tickets.yml