Metadata-Version: 2.1
Name: pyosticket
Version: 0.1.0
Summary: Python client for os ticket
Home-page: https://github.com/joeirimpan/pyosticket
Author: Joe Irimpan
Author-email: joeirimpan@gmail.com
License: MIT license
Keywords: pyosticket
Platform: UNKNOWN
Classifier: Development Status :: 2 - Pre-Alpha
Classifier: Intended Audience :: Developers
Classifier: License :: OSI Approved :: MIT License
Classifier: Natural Language :: English
Classifier: Programming Language :: Python :: 2
Classifier: Programming Language :: Python :: 2.7
Classifier: Programming Language :: Python :: 3
Classifier: Programming Language :: Python :: 3.4
Classifier: Programming Language :: Python :: 3.5
Classifier: Programming Language :: Python :: 3.6
Classifier: Programming Language :: Python :: 3.7
